R4/__init__.py
R4-0.0.2.dist-info/LICENCE
R4-0.0.2.dist-info/METADATA
R4-0.0.2.dist-info/WHEEL
R4-0.0.2.dist-info/top_level.txt
R4-0.0.2.dist-info/RECORD
