Metadata-Version: 2.1
Name: R4
Version: 0.0.2
Summary: R4 is a python package for encrypt your important data
Home-page: https://github.com/rizki4106/R4.git
Author-email: rizkimaulana348@gmail.com
License: MIT
Download-URL: https://github.com/rizki4106/R4/archive/master.zip
Keywords: encrypt,decrypt,base64,base64_encode,base64_decode,md5
Platform: UNKNOWN
Classifier: Programming Language :: Python :: 2.7
Classifier: Programming Language :: Python :: 3
